slack_client-0.3.0.dist-info/RECORD
slack_client-0.3.0.dist-info/top_level.txt
slack_client-0.3.0.dist-info/DESCRIPTION.rst
slack_client-0.3.0.dist-info/WHEEL
slack_client-0.3.0.dist-info/metadata.json
slack_client-0.3.0.dist-info/METADATA
slack_client/api.py
slack_client/channel.py
slack_client/exceptions.py
slack_client/__init__.py
